droopssnowflake/__init__.py
droopssnowflake/droops_snowflake.py
droops_snowflake-1.0.1.dist-info/LICENSE
droops_snowflake-1.0.1.dist-info/METADATA
droops_snowflake-1.0.1.dist-info/WHEEL
droops_snowflake-1.0.1.dist-info/top_level.txt
droops_snowflake-1.0.1.dist-info/RECORD
