Metadata-Version: 2.1
Name: droops-snowflake
Version: 1.0.1
Summary: Snowflake generator.
Home-page: https://github.com/JohnyTheCarrot/snowflake
Author: JohnyTheCarrot
Author-email: johnythecarrot@gmail.com
License: UNKNOWN
Platform: UNKNOWN
